Metadata-Version: 2.4
Name: bgweb
Version: 0.10.1
Summary: BBGLab web framework
Home-page: https://bitbucket.org/bgframework/bgweb
Author: Barcelona Biomedical Genomics Lab
Author-email: bbglab@irbbarcelona.org
Project-URL: BBGLab website, https://bbglab.irbbarcelona.org
License-File: LICENSE.txt
Requires-Dist: bgcluster
Requires-Dist: CherryPy
Requires-Dist: requests
Requires-Dist: requests-oauthlib
Dynamic: author
Dynamic: author-email
Dynamic: description
Dynamic: description-content-type
Dynamic: home-page
Dynamic: license-file
Dynamic: project-url
Dynamic: requires-dist
Dynamic: summary
